<?xml version="1.0"?>
<images>
	<image><![CDATA[coveredito.jpg]]></image>
	<image><![CDATA[e003.jpg]]></image>
	<image><![CDATA[e004.jpg]]></image>
	<image><![CDATA[e005.jpg]]></image>
	<image><![CDATA[e006.jpg]]></image>
	<image><![CDATA[e007.jpg]]></image>						
	<image><![CDATA[e008.jpg]]></image>
	<image><![CDATA[e009.jpg]]></image>
	<image><![CDATA[e010.jpg]]></image>
	<image><![CDATA[e011.jpg]]></image>
	<image><![CDATA[el_edito2.jpg]]></image>
	<image><![CDATA[el_edito3.jpg]]></image>
	<image><![CDATA[el_edito4.jpg]]></image>
	<image><![CDATA[edito1.jpg]]></image>
	<image><![CDATA[e012.jpg]]></image>
	<image><![CDATA[e013.jpg]]></image>
	<image><![CDATA[e014.jpg]]></image>
	<image><![CDATA[e015.jpg]]></image>						
	<image><![CDATA[e016.jpg]]></image>
	<image><![CDATA[e017.jpg]]></image>
	<image><![CDATA[e018.jpg]]></image>
	<image><![CDATA[e019.jpg]]></image>
	<image><![CDATA[e020.jpg]]></image>
	<image><![CDATA[fbfashion.jpg]]></image>
	<image><![CDATA[fbfashion2.jpg]]></image>	
	<image><![CDATA[e021.jpg]]></image>
	<image><![CDATA[e022.jpg]]></image>
	<image><![CDATA[e023.jpg]]></image>						
	<image><![CDATA[e024.jpg]]></image>
	<image><![CDATA[e025.jpg]]></image>
	<image><![CDATA[e026.jpg]]></image>
	<image><![CDATA[e027.jpg]]></image>
	<image><![CDATA[e028.jpg]]></image>
	<image><![CDATA[e029.jpg]]></image>
	<image><![CDATA[e030.jpg]]></image>
	<image><![CDATA[e031.jpg]]></image>						
	<image><![CDATA[e032.jpg]]></image>
	<image><![CDATA[e033.jpg]]></image>
	<image><![CDATA[e034.jpg]]></image>
	<image><![CDATA[e035.jpg]]></image>						
	<image><![CDATA[e037.jpg]]></image>
	<image><![CDATA[e038.jpg]]></image>
	<image><![CDATA[e039.jpg]]></image>
	<image><![CDATA[e040.jpg]]></image>
	<image><![CDATA[e041.jpg]]></image>
	<image><![CDATA[e042.jpg]]></image>
	<image><![CDATA[e043.jpg]]></image>						
	<image><![CDATA[e044.jpg]]></image>
	<image><![CDATA[e045.jpg]]></image>
	<image><![CDATA[e046.jpg]]></image>
	<image><![CDATA[e047.jpg]]></image>
	<image><![CDATA[e048.jpg]]></image>
	<image><![CDATA[e049.jpg]]></image>
	<image><![CDATA[e050.jpg]]></image>
	<image><![CDATA[e051.jpg]]></image>						
	<image><![CDATA[e052.jpg]]></image>
	<image><![CDATA[e053.jpg]]></image>
	<image><![CDATA[e054.jpg]]></image>
	<image><![CDATA[e055.jpg]]></image>
	<image><![CDATA[e056.jpg]]></image>
	<image><![CDATA[e057.jpg]]></image>
	<image><![CDATA[e058.jpg]]></image>
	<image><![CDATA[e059.jpg]]></image>						
	<image><![CDATA[e060.jpg]]></image>
	<image><![CDATA[e061.jpg]]></image>	
	<image><![CDATA[e062.jpg]]></image>
	<image><![CDATA[e063.jpg]]></image>
	<image><![CDATA[e064.jpg]]></image>
	<image><![CDATA[e065.jpg]]></image>						
	<image><![CDATA[e066.jpg]]></image>
	<image><![CDATA[e067.jpg]]></image>
	<image><![CDATA[e068.jpg]]></image>
	<image><![CDATA[e069.jpg]]></image>
	<image><![CDATA[e070.jpg]]></image>
	<image><![CDATA[e071.jpg]]></image>
	<image><![CDATA[e072.jpg]]></image>
	<image><![CDATA[e073.jpg]]></image>						
	<image><![CDATA[e074.jpg]]></image>
	<image><![CDATA[e075.jpg]]></image>	
	<image><![CDATA[e076.jpg]]></image>
	<image><![CDATA[e077.jpg]]></image>						
	<image><![CDATA[e078.jpg]]></image>
	<image><![CDATA[e079.jpg]]></image>	
	<image><![CDATA[e080.jpg]]></image>
	<image><![CDATA[e081.jpg]]></image>						
	<image><![CDATA[e082.jpg]]></image>
	<image><![CDATA[e083.jpg]]></image>	
	<image><![CDATA[e084.jpg]]></image>
	<image><![CDATA[e085.jpg]]></image>						
	<image><![CDATA[e086.jpg]]></image>
	<image><![CDATA[e087.jpg]]></image>
	<image><![CDATA[e088.jpg]]></image>	
</images>